MANIFEST.in
README.rst
setup.py
admin_view_permission/__init__.py
admin_view_permission/admin.py
admin_view_permission/apps.py
admin_view_permission/enums.py
admin_view_permission/utils.py
django_admin_view_permission.egg-info/PKG-INFO
django_admin_view_permission.egg-info/SOURCES.txt
django_admin_view_permission.egg-info/dependency_links.txt
django_admin_view_permission.egg-info/requires.txt
django_admin_view_permission.egg-info/top_level.txt