Metadata-Version: 1.1
Name: django-admin-view-permission
Version: 0.4
Summary: A simple Django app which adds view permissions.
Home-page: http://django-admin-view-permission.readthedocs.org/
Author: UNKNOWN
Author-email: UNKNOWN
License: BSD License
Keywords: django,admin
Platform: UNKNOWN
Classifier: Development Status :: 5 - Production/Stable
Classifier: Environment :: Web Environment
Classifier: Framework :: Django
Classifier: Framework :: Django :: 1.9
Classifier: Intended Audience :: Developers
Classifier: License :: OSI Approved :: BSD License
Classifier: Operating System :: OS Independent
Classifier: Programming Language :: Python
Classifier: Programming Language :: Python :: 2.7
Classifier: Programming Language :: Python :: 3.4
Classifier: Programming Language :: Python :: 3.5
Classifier: Topic :: Internet :: WWW/HTTP
Classifier: Topic :: Internet :: WWW/HTTP :: Dynamic Content
